vuv/__init__.py
virtual_uv-0.1.4.dist-info/METADATA
virtual_uv-0.1.4.dist-info/WHEEL
virtual_uv-0.1.4.dist-info/entry_points.txt
virtual_uv-0.1.4.dist-info/licenses/LICENSE
virtual_uv-0.1.4.dist-info/RECORD
