Metadata-Version: 2.4
Name: virtual-uv
Version: 0.1.4
Summary: A wrapper script for uv enabling automatic virtual environment detection and configuration.
Author-email: MilkClouds <milkclouds00@gmail.com>
License-File: LICENSE
Requires-Python: >=3.7
